[
    {
        "id": 1,
        "nome": "Florentina",
        "funcao": "Caixa",
        "idade": "28 anos",
        "acesso ao sistema": true 
    },
    {
        "id": 2,
        "nome": "Virgulino",
        "funcao": "Vendedor",
        "idade": "26 anos",
        "acesso ao sistema": true
    },
    {
        "id": 3,
        "nome": "Sérgio",
        "funcao": "Serviços Gerais",
        "idade": "29 anos",
        "acesso ao sistema": false
    },
    {
        "id": 4,
        "nome": "Maria",
        "funcao": "Supervisora",
        "idade": "30 anos",
        "acesso ao sistema": true
    },
    {
        "id": 5,
        "nome": "João",
        "funcao": "Vendedor",
        "idade": "21 anos",
        "acesso ao sistema": true 
    },
    {
        "id": 6,
        "nome": "Fernanda",
        "funcao": "Auxiliar Administrativa",
        "idade": "29 anos",
        "acesso ao sistema": true 
    },
    {
        "id": 7,
        "nome": "Noel",
        "funcao": "Auxiliar de estoque",
        "idade": "25 anos",
        "acesso ao sistema": true
    },
    {
        "id": 8,
        "nome": "Joaquina",
        "funcao": "Caixa",
        "idade": "31 anos",
        "acesso ao sistema": true 
    },
    {
        "id": 9,
        "nome": "Rebeca",
        "funcao": "Estagiária",
        "idade": "20 anos",
        "acesso ao sistema": false 
    },
    {
        "id": 10,
        "nome": "Marcelo",
        "funcao": "Segurança",
        "idade": "33 anos",
        "acesso ao sistema": false 
    }
]